Workbook

Sheet Instructions
B2: UK Landlord Income & Expense Tracker 2026/27
B3: HMRC SA105 Ready | Making Tax Digital Compatible | Multi-Property
B5: HOW TO USE THIS SPREADSHEET
B7: 1. Set up your properties
B8: Go to the 'Property Setup' tab and enter your property details (address, purchase price, mortgage info). You can track up to 10 properties.
B10: 2. Record transactions monthly
B11: Each month has its own tab (Apr through Mar, matching the UK tax year). Enter your rental income and expenses as they occur.
B13: 3. Use UK tax categories
B14: Expense categories match HMRC Self Assessment form SA105 boxes. This makes filling your tax return much easier.
B16: 4. Check quarterly summaries
B17: The 'Quarterly MTD' tab automatically calculates your quarterly figures for Making Tax Digital submissions (Q1: Apr-Jun, Q2: Jul-Sep, Q3: Oct-Dec, Q4: Jan-Mar).
B19: 5. Review your annual summary
... B25: COLOUR GUIDE
B27: Blue text on light yellow | C27: Cells where YOU enter data
B28: Bold black text | C28: Calculated automatically — do not edit
B29: Green background | C29: Positive result / profit
B30: Red background | C30: Negative result / loss or deadline warning
B33: IMPORTANT DATES 2026/27 TAX YEAR
B35: 6 April 2026 | C35: Tax year starts — begin recording from this date
B36: 7 August 2026 | C36: MTD Q1 quarterly update deadline (Apr-Jun)
B37: 7 November 2026 | C37: MTD Q2 quarterly update deadline (Jul-Sep)
B38: 7 February 2027 | C38: MTD Q3 quarterly update deadline (Oct-Dec)
B39: 5 April 2027 | C39: Tax year ends
B40: 7 May 2027 | C40: MTD Q4 quarterly update deadline (Jan-Mar)
B41: 31 January 2028 | C41: Self Assessment tax return deadline for 2026/27
B44: Disclaimer: This spreadsheet is a bookkeeping tool and does not constitute tax advice. Always consult a qualified accountant for your specific tax situation.

Sheet Property Setup
B2: Property Portfolio Setup
B3: Enter your property details below. Blue cells are for your input.
B5: Detail | C5: Property 1 | D5: Property 2 | E5: Property 3 | F5: Property 4 | G5: Property 5 | H5: Property 6 | I5: Property 7 | J5: Property 8 | K5: Property 9 | L5: Property 10
B6: Property Name / Reference
B7: Address Line 1
B8: Postcode
B9: Property Type (House/Flat/HMO)
B10: Date Acquired
B11: Purchase Price (£)
B12: Current Estimated Value (£)
B13: Mortgage Outstanding (£)
B14: Monthly Mortgage Payment (£)
B15: Mortgage Interest Rate (%)
B16: Annual Mortgage Interest (£) | C16: =IF(C13="",0,C13*C15) -> 0 | D16: =IF(D13="",0,D13*D15) -> 0 | E16: =IF(E13="",0,E13*E15) -> 0 | F16: =IF(F13="",0,F13*F15) -> 0 | G16: =IF(G13="",0,G13*G15) -> 0 | H16: =IF(H13="",0,H13*H15) -> 0 | I16: =IF(I13="",0,I13*I15) -> 0 | J16: =IF(J13="",0,J13*J15) -> 0 | ... L16: =IF(L13="",0,L13*L15) -> 0
B17: Monthly Rent (£)
B18: Tenancy Start Date
B19: Tenant Name(s)
B20: Letting Agent (if any)
B21: EPC Rating
B22: Gas Safety Cert Expiry
B23: EICR Expiry
B24: EPC Expiry

Sheet Apr
B2: April 2026 — Income & Expenses
B3: Tax Year 2026/27 | Quarter 1 | Enter amounts in blue cells
B5: Category | C5: ='Property Setup'!C6 -> 0 | D5: ='Property Setup'!D6 -> 0 | E5: ='Property Setup'!E6 -> 0 | F5: ='Property Setup'!F6 -> 0 | G5: ='Property Setup'!G6 -> 0 | H5: ='Property Setup'!H6 -> 0 | I5: ='Property Setup'!I6 -> 0 | J5: ='Property Setup'!J6 -> 0 | ... L5: ='Property Setup'!L6 -> 0 | M5: TOTAL
B6: INCOME
B7: Rental Income Received | M7: =SUM(C7:L7) -> 0
B8: Other Property Income | M8: =SUM(C8:L8) -> 0
B9: TOTAL INCOME | C9: =SUM(C7:C8) -> 0 | D9: =SUM(D7:D8) -> 0 | E9: =SUM(E7:E8) -> 0 | F9: =SUM(F7:F8) -> 0 | G9: =SUM(G7:G8) -> 0 | H9: =SUM(H7:H8) -> 0 | I9: =SUM(I7:I8) -> 0 | J9: =SUM(J7:J8) -> 0 | ... M9: =SUM(M7:M8) -> 0
B11: EXPENSES (HMRC SA105 Categories)
B12: Rent, rates, insurance & ground rent | M12: =SUM(C12:L12) -> 0
B13: Property repairs & maintenance | M13: =SUM(C13:L13) -> 0
B14: Loan interest & financial costs | M14: =SUM(C14:L14) -> 0
B15: Legal, management & professional fees | M15: =SUM(C15:L15) -> 0
B16: Cost of services (inc. wages) | M16: =SUM(C16:L16) -> 0
B17: Travel & vehicle costs | M17: =SUM(C17:L17) -> 0
B18: Allowable other expenses | M18: =SUM(C18:L18) -> 0
B19: TOTAL EXPENSES | C19: =SUM(C12:C18) -> 0 | D19: =SUM(D12:D18) -> 0 | E19: =SUM(E12:E18) -> 0 | F19: =SUM(F12:F18) -> 0 | G19: =SUM(G12:G18) -> 0 | H19: =SUM(H12:H18) -> 0 | I19: =SUM(I12:I18) -> 0 | J19: =SUM(J12:J18) -> 0 | ... M19: =SUM(M12:M18) -> 0
B21: NET PROFIT / (LOSS) | C21: =C9-C19 -> 0 | D21: =D9-D19 -> 0 | E21: =E9-E19 -> 0 | F21: =F9-F19 -> 0 | G21: =G9-G19 -> 0 | H21: =H9-H19 -> 0 | I21: =I9-I19 -> 0 | J21: =J9-J19 -> 0 | ... M21: =M9-M19 -> 0
B23: SA105 Reference: Box 20 = Total rents, Box 25-31 = Expenses by category. Hover over expense names for SA105 box references.

Sheet May
B2: May 2026 — Income & Expenses
B3: Tax Year 2026/27 | Quarter 1 | Enter amounts in blue cells
B5: Category | C5: ='Property Setup'!C6 -> 0 | D5: ='Property Setup'!D6 -> 0 | E5: ='Property Setup'!E6 -> 0 | F5: ='Property Setup'!F6 -> 0 | G5: ='Property Setup'!G6 -> 0 | H5: ='Property Setup'!H6 -> 0 | I5: ='Property Setup'!I6 -> 0 | J5: ='Property Setup'!J6 -> 0 | ... L5: ='Property Setup'!L6 -> 0 | M5: TOTAL
B6: INCOME
B7: Rental Income Received | M7: =SUM(C7:L7) -> 0
B8: Other Property Income | M8: =SUM(C8:L8) -> 0
B9: TOTAL INCOME | C9: =SUM(C7:C8) -> 0 | D9: =SUM(D7:D8) -> 0 | E9: =SUM(E7:E8) -> 0 | F9: =SUM(F7:F8) -> 0 | G9: =SUM(G7:G8) -> 0 | H9: =SUM(H7:H8) -> 0 | I9: =SUM(I7:I8) -> 0 | J9: =SUM(J7:J8) -> 0 | ... M9: =SUM(M7:M8) -> 0
B11: EXPENSES (HMRC SA105 Categories)
B12: Rent, rates, insurance & ground rent | M12: =SUM(C12:L12) -> 0
B13: Property repairs & maintenance | M13: =SUM(C13:L13) -> 0
B14: Loan interest & financial costs | M14: =SUM(C14:L14) -> 0
B15: Legal, management & professional fees | M15: =SUM(C15:L15) -> 0
B16: Cost of services (inc. wages) | M16: =SUM(C16:L16) -> 0
B17: Travel & vehicle costs | M17: =SUM(C17:L17) -> 0
B18: Allowable other expenses | M18: =SUM(C18:L18) -> 0
B19: TOTAL EXPENSES | C19: =SUM(C12:C18) -> 0 | D19: =SUM(D12:D18) -> 0 | E19: =SUM(E12:E18) -> 0 | F19: =SUM(F12:F18) -> 0 | G19: =SUM(G12:G18) -> 0 | H19: =SUM(H12:H18) -> 0 | I19: =SUM(I12:I18) -> 0 | J19: =SUM(J12:J18) -> 0 | ... M19: =SUM(M12:M18) -> 0
B21: NET PROFIT / (LOSS) | C21: =C9-C19 -> 0 | D21: =D9-D19 -> 0 | E21: =E9-E19 -> 0 | F21: =F9-F19 -> 0 | G21: =G9-G19 -> 0 | H21: =H9-H19 -> 0 | I21: =I9-I19 -> 0 | J21: =J9-J19 -> 0 | ... M21: =M9-M19 -> 0
B23: SA105 Reference: Box 20 = Total rents, Box 25-31 = Expenses by category. Hover over expense names for SA105 box references.

Sheet Jun
B2: June 2026 — Income & Expenses
B3: Tax Year 2026/27 | Quarter 1 | Enter amounts in blue cells
B5: Category | C5: ='Property Setup'!C6 -> 0 | D5: ='Property Setup'!D6 -> 0 | E5: ='Property Setup'!E6 -> 0 | F5: ='Property Setup'!F6 -> 0 | G5: ='Property Setup'!G6 -> 0 | H5: ='Property Setup'!H6 -> 0 | I5: ='Property Setup'!I6 -> 0 | J5: ='Property Setup'!J6 -> 0 | ... L5: ='Property Setup'!L6 -> 0 | M5: TOTAL
B6: INCOME
B7: Rental Income Received | M7: =SUM(C7:L7) -> 0
B8: Other Property Income | M8: =SUM(C8:L8) -> 0
B9: TOTAL INCOME | C9: =SUM(C7:C8) -> 0 | D9: =SUM(D7:D8) -> 0 | E9: =SUM(E7:E8) -> 0 | F9: =SUM(F7:F8) -> 0 | G9: =SUM(G7:G8) -> 0 | H9: =SUM(H7:H8) -> 0 | I9: =SUM(I7:I8) -> 0 | J9: =SUM(J7:J8) -> 0 | ... M9: =SUM(M7:M8) -> 0
B11: EXPENSES (HMRC SA105 Categories)
B12: Rent, rates, insurance & ground rent | M12: =SUM(C12:L12) -> 0
B13: Property repairs & maintenance | M13: =SUM(C13:L13) -> 0
B14: Loan interest & financial costs | M14: =SUM(C14:L14) -> 0
B15: Legal, management & professional fees | M15: =SUM(C15:L15) -> 0
B16: Cost of services (inc. wages) | M16: =SUM(C16:L16) -> 0
B17: Travel & vehicle costs | M17: =SUM(C17:L17) -> 0
B18: Allowable other expenses | M18: =SUM(C18:L18) -> 0
B19: TOTAL EXPENSES | C19: =SUM(C12:C18) -> 0 | D19: =SUM(D12:D18) -> 0 | E19: =SUM(E12:E18) -> 0 | F19: =SUM(F12:F18) -> 0 | G19: =SUM(G12:G18) -> 0 | H19: =SUM(H12:H18) -> 0 | I19: =SUM(I12:I18) -> 0 | J19: =SUM(J12:J18) -> 0 | ... M19: =SUM(M12:M18) -> 0
B21: NET PROFIT / (LOSS) | C21: =C9-C19 -> 0 | D21: =D9-D19 -> 0 | E21: =E9-E19 -> 0 | F21: =F9-F19 -> 0 | G21: =G9-G19 -> 0 | H21: =H9-H19 -> 0 | I21: =I9-I19 -> 0 | J21: =J9-J19 -> 0 | ... M21: =M9-M19 -> 0
B23: SA105 Reference: Box 20 = Total rents, Box 25-31 = Expenses by category. Hover over expense names for SA105 box references.

Sheet Jul
B2: July 2026 — Income & Expenses
B3: Tax Year 2026/27 | Quarter 2 | Enter amounts in blue cells
B5: Category | C5: ='Property Setup'!C6 -> 0 | D5: ='Property Setup'!D6 -> 0 | E5: ='Property Setup'!E6 -> 0 | F5: ='Property Setup'!F6 -> 0 | G5: ='Property Setup'!G6 -> 0 | H5: ='Property Setup'!H6 -> 0 | I5: ='Property Setup'!I6 -> 0 | J5: ='Property Setup'!J6 -> 0 | ... L5: ='Property Setup'!L6 -> 0 | M5: TOTAL
B6: INCOME
B7: Rental Income Received | M7: =SUM(C7:L7) -> 0
B8: Other Property Income | M8: =SUM(C8:L8) -> 0
B9: TOTAL INCOME | C9: =SUM(C7:C8) -> 0 | D9: =SUM(D7:D8) -> 0 | E9: =SUM(E7:E8) -> 0 | F9: =SUM(F7:F8) -> 0 | G9: =SUM(G7:G8) -> 0 | H9: =SUM(H7:H8) -> 0 | I9: =SUM(I7:I8) -> 0 | J9: =SUM(J7:J8) -> 0 | ... M9: =SUM(M7:M8) -> 0
B11: EXPENSES (HMRC SA105 Categories)
B12: Rent, rates, insurance & ground rent | M12: =SUM(C12:L12) -> 0
B13: Property repairs & maintenance | M13: =SUM(C13:L13) -> 0
B14: Loan interest & financial costs | M14: =SUM(C14:L14) -> 0
B15: Legal, management & professional fees | M15: =SUM(C15:L15) -> 0
B16: Cost of services (inc. wages) | M16: =SUM(C16:L16) -> 0
B17: Travel & vehicle costs | M17: =SUM(C17:L17) -> 0
B18: Allowable other expenses | M18: =SUM(C18:L18) -> 0
B19: TOTAL EXPENSES | C19: =SUM(C12:C18) -> 0 | D19: =SUM(D12:D18) -> 0 | E19: =SUM(E12:E18) -> 0 | F19: =SUM(F12:F18) -> 0 | G19: =SUM(G12:G18) -> 0 | H19: =SUM(H12:H18) -> 0 | I19: =SUM(I12:I18) -> 0 | J19: =SUM(J12:J18) -> 0 | ... M19: =SUM(M12:M18) -> 0
B21: NET PROFIT / (LOSS) | C21: =C9-C19 -> 0 | D21: =D9-D19 -> 0 | E21: =E9-E19 -> 0 | F21: =F9-F19 -> 0 | G21: =G9-G19 -> 0 | H21: =H9-H19 -> 0 | I21: =I9-I19 -> 0 | J21: =J9-J19 -> 0 | ... M21: =M9-M19 -> 0
B23: SA105 Reference: Box 20 = Total rents, Box 25-31 = Expenses by category. Hover over expense names for SA105 box references.

Sheet Aug
B2: August 2026 — Income & Expenses
B3: Tax Year 2026/27 | Quarter 2 | Enter amounts in blue cells
B5: Category | C5: ='Property Setup'!C6 -> 0 | D5: ='Property Setup'!D6 -> 0 | E5: ='Property Setup'!E6 -> 0 | F5: ='Property Setup'!F6 -> 0 | G5: ='Property Setup'!G6 -> 0 | H5: ='Property Setup'!H6 -> 0 | I5: ='Property Setup'!I6 -> 0 | J5: ='Property Setup'!J6 -> 0 | ... L5: ='Property Setup'!L6 -> 0 | M5: TOTAL
B6: INCOME
B7: Rental Income Received | M7: =SUM(C7:L7) -> 0
B8: Other Property Income | M8: =SUM(C8:L8) -> 0
B9: TOTAL INCOME | C9: =SUM(C7:C8) -> 0 | D9: =SUM(D7:D8) -> 0 | E9: =SUM(E7:E8) -> 0 | F9: =SUM(F7:F8) -> 0 | G9: =SUM(G7:G8) -> 0 | H9: =SUM(H7:H8) -> 0 | I9: =SUM(I7:I8) -> 0 | J9: =SUM(J7:J8) -> 0 | ... M9: =SUM(M7:M8) -> 0
B11: EXPENSES (HMRC SA105 Categories)
B12: Rent, rates, insurance & ground rent | M12: =SUM(C12:L12) -> 0
B13: Property repairs & maintenance | M13: =SUM(C13:L13) -> 0
B14: Loan interest & financial costs | M14: =SUM(C14:L14) -> 0
B15: Legal, management & professional fees | M15: =SUM(C15:L15) -> 0
B16: Cost of services (inc. wages) | M16: =SUM(C16:L16) -> 0
B17: Travel & vehicle costs | M17: =SUM(C17:L17) -> 0
B18: Allowable other expenses | M18: =SUM(C18:L18) -> 0
B19: TOTAL EXPENSES | C19: =SUM(C12:C18) -> 0 | D19: =SUM(D12:D18) -> 0 | E19: =SUM(E12:E18) -> 0 | F19: =SUM(F12:F18) -> 0 | G19: =SUM(G12:G18) -> 0 | H19: =SUM(H12:H18) -> 0 | I19: =SUM(I12:I18) -> 0 | J19: =SUM(J12:J18) -> 0 | ... M19: =SUM(M12:M18) -> 0
B21: NET PROFIT / (LOSS) | C21: =C9-C19 -> 0 | D21: =D9-D19 -> 0 | E21: =E9-E19 -> 0 | F21: =F9-F19 -> 0 | G21: =G9-G19 -> 0 | H21: =H9-H19 -> 0 | I21: =I9-I19 -> 0 | J21: =J9-J19 -> 0 | ... M21: =M9-M19 -> 0
B23: SA105 Reference: Box 20 = Total rents, Box 25-31 = Expenses by category. Hover over expense names for SA105 box references.

Sheet Sep
B2: September 2026 — Income & Expenses
B3: Tax Year 2026/27 | Quarter 2 | Enter amounts in blue cells
B5: Category | C5: ='Property Setup'!C6 -> 0 | D5: ='Property Setup'!D6 -> 0 | E5: ='Property Setup'!E6 -> 0 | F5: ='Property Setup'!F6 -> 0 | G5: ='Property Setup'!G6 -> 0 | H5: ='Property Setup'!H6 -> 0 | I5: ='Property Setup'!I6 -> 0 | J5: ='Property Setup'!J6 -> 0 | ... L5: ='Property Setup'!L6 -> 0 | M5: TOTAL
B6: INCOME
B7: Rental Income Received | M7: =SUM(C7:L7) -> 0
B8: Other Property Income | M8: =SUM(C8:L8) -> 0
B9: TOTAL INCOME | C9: =SUM(C7:C8) -> 0 | D9: =SUM(D7:D8) -> 0 | E9: =SUM(E7:E8) -> 0 | F9: =SUM(F7:F8) -> 0 | G9: =SUM(G7:G8) -> 0 | H9: =SUM(H7:H8) -> 0 | I9: =SUM(I7:I8) -> 0 | J9: =SUM(J7:J8) -> 0 | ... M9: =SUM(M7:M8) -> 0
B11: EXPENSES (HMRC SA105 Categories)
B12: Rent, rates, insurance & ground rent | M12: =SUM(C12:L12) -> 0
B13: Property repairs & maintenance | M13: =SUM(C13:L13) -> 0
B14: Loan interest & financial costs | M14: =SUM(C14:L14) -> 0
B15: Legal, management & professional fees | M15: =SUM(C15:L15) -> 0
B16: Cost of services (inc. wages) | M16: =SUM(C16:L16) -> 0
B17: Travel & vehicle costs | M17: =SUM(C17:L17) -> 0
B18: Allowable other expenses | M18: =SUM(C18:L18) -> 0
B19: TOTAL EXPENSES | C19: =SUM(C12:C18) -> 0 | D19: =SUM(D12:D18) -> 0 | E19: =SUM(E12:E18) -> 0 | F19: =SUM(F12:F18) -> 0 | G19: =SUM(G12:G18) -> 0 | H19: =SUM(H12:H18) -> 0 | I19: =SUM(I12:I18) -> 0 | J19: =SUM(J12:J18) -> 0 | ... M19: =SUM(M12:M18) -> 0
B21: NET PROFIT / (LOSS) | C21: =C9-C19 -> 0 | D21: =D9-D19 -> 0 | E21: =E9-E19 -> 0 | F21: =F9-F19 -> 0 | G21: =G9-G19 -> 0 | H21: =H9-H19 -> 0 | I21: =I9-I19 -> 0 | J21: =J9-J19 -> 0 | ... M21: =M9-M19 -> 0
B23: SA105 Reference: Box 20 = Total rents, Box 25-31 = Expenses by category. Hover over expense names for SA105 box references.

Sheet Oct
B2: October 2026 — Income & Expenses
B3: Tax Year 2026/27 | Quarter 3 | Enter amounts in blue cells
B5: Category | C5: ='Property Setup'!C6 -> 0 | D5: ='Property Setup'!D6 -> 0 | E5: ='Property Setup'!E6 -> 0 | F5: ='Property Setup'!F6 -> 0 | G5: ='Property Setup'!G6 -> 0 | H5: ='Property Setup'!H6 -> 0 | I5: ='Property Setup'!I6 -> 0 | J5: ='Property Setup'!J6 -> 0 | ... L5: ='Property Setup'!L6 -> 0 | M5: TOTAL
B6: INCOME
B7: Rental Income Received | M7: =SUM(C7:L7) -> 0
B8: Other Property Income | M8: =SUM(C8:L8) -> 0
B9: TOTAL INCOME | C9: =SUM(C7:C8) -> 0 | D9: =SUM(D7:D8) -> 0 | E9: =SUM(E7:E8) -> 0 | F9: =SUM(F7:F8) -> 0 | G9: =SUM(G7:G8) -> 0 | H9: =SUM(H7:H8) -> 0 | I9: =SUM(I7:I8) -> 0 | J9: =SUM(J7:J8) -> 0 | ... M9: =SUM(M7:M8) -> 0
B11: EXPENSES (HMRC SA105 Categories)
B12: Rent, rates, insurance & ground rent | M12: =SUM(C12:L12) -> 0
B13: Property repairs & maintenance | M13: =SUM(C13:L13) -> 0
B14: Loan interest & financial costs | M14: =SUM(C14:L14) -> 0
B15: Legal, management & professional fees | M15: =SUM(C15:L15) -> 0
B16: Cost of services (inc. wages) | M16: =SUM(C16:L16) -> 0
B17: Travel & vehicle costs | M17: =SUM(C17:L17) -> 0
B18: Allowable other expenses | M18: =SUM(C18:L18) -> 0
B19: TOTAL EXPENSES | C19: =SUM(C12:C18) -> 0 | D19: =SUM(D12:D18) -> 0 | E19: =SUM(E12:E18) -> 0 | F19: =SUM(F12:F18) -> 0 | G19: =SUM(G12:G18) -> 0 | H19: =SUM(H12:H18) -> 0 | I19: =SUM(I12:I18) -> 0 | J19: =SUM(J12:J18) -> 0 | ... M19: =SUM(M12:M18) -> 0
B21: NET PROFIT / (LOSS) | C21: =C9-C19 -> 0 | D21: =D9-D19 -> 0 | E21: =E9-E19 -> 0 | F21: =F9-F19 -> 0 | G21: =G9-G19 -> 0 | H21: =H9-H19 -> 0 | I21: =I9-I19 -> 0 | J21: =J9-J19 -> 0 | ... M21: =M9-M19 -> 0
B23: SA105 Reference: Box 20 = Total rents, Box 25-31 = Expenses by category. Hover over expense names for SA105 box references.

Sheet Nov
B2: November 2026 — Income & Expenses
B3: Tax Year 2026/27 | Quarter 3 | Enter amounts in blue cells
B5: Category | C5: ='Property Setup'!C6 -> 0 | D5: ='Property Setup'!D6 -> 0 | E5: ='Property Setup'!E6 -> 0 | F5: ='Property Setup'!F6 -> 0 | G5: ='Property Setup'!G6 -> 0 | H5: ='Property Setup'!H6 -> 0 | I5: ='Property Setup'!I6 -> 0 | J5: ='Property Setup'!J6 -> 0 | ... L5: ='Property Setup'!L6 -> 0 | M5: TOTAL
B6: INCOME
B7: Rental Income Received | M7: =SUM(C7:L7) -> 0
B8: Other Property Income | M8: =SUM(C8:L8) -> 0
B9: TOTAL INCOME | C9: =SUM(C7:C8) -> 0 | D9: =SUM(D7:D8) -> 0 | E9: =SUM(E7:E8) -> 0 | F9: =SUM(F7:F8) -> 0 | G9: =SUM(G7:G8) -> 0 | H9: =SUM(H7:H8) -> 0 | I9: =SUM(I7:I8) -> 0 | J9: =SUM(J7:J8) -> 0 | ... M9: =SUM(M7:M8) -> 0
B11: EXPENSES (HMRC SA105 Categories)
B12: Rent, rates, insurance & ground rent | M12: =SUM(C12:L12) -> 0
B13: Property repairs & maintenance | M13: =SUM(C13:L13) -> 0
B14: Loan interest & financial costs | M14: =SUM(C14:L14) -> 0
B15: Legal, management & professional fees | M15: =SUM(C15:L15) -> 0
B16: Cost of services (inc. wages) | M16: =SUM(C16:L16) -> 0
B17: Travel & vehicle costs | M17: =SUM(C17:L17) -> 0
B18: Allowable other expenses | M18: =SUM(C18:L18) -> 0
B19: TOTAL EXPENSES | C19: =SUM(C12:C18) -> 0 | D19: =SUM(D12:D18) -> 0 | E19: =SUM(E12:E18) -> 0 | F19: =SUM(F12:F18) -> 0 | G19: =SUM(G12:G18) -> 0 | H19: =SUM(H12:H18) -> 0 | I19: =SUM(I12:I18) -> 0 | J19: =SUM(J12:J18) -> 0 | ... M19: =SUM(M12:M18) -> 0
B21: NET PROFIT / (LOSS) | C21: =C9-C19 -> 0 | D21: =D9-D19 -> 0 | E21: =E9-E19 -> 0 | F21: =F9-F19 -> 0 | G21: =G9-G19 -> 0 | H21: =H9-H19 -> 0 | I21: =I9-I19 -> 0 | J21: =J9-J19 -> 0 | ... M21: =M9-M19 -> 0
B23: SA105 Reference: Box 20 = Total rents, Box 25-31 = Expenses by category. Hover over expense names for SA105 box references.

Sheet Dec
B2: December 2026 — Income & Expenses
B3: Tax Year 2026/27 | Quarter 3 | Enter amounts in blue cells
B5: Category | C5: ='Property Setup'!C6 -> 0 | D5: ='Property Setup'!D6 -> 0 | E5: ='Property Setup'!E6 -> 0 | F5: ='Property Setup'!F6 -> 0 | G5: ='Property Setup'!G6 -> 0 | H5: ='Property Setup'!H6 -> 0 | I5: ='Property Setup'!I6 -> 0 | J5: ='Property Setup'!J6 -> 0 | ... L5: ='Property Setup'!L6 -> 0 | M5: TOTAL
B6: INCOME
B7: Rental Income Received | M7: =SUM(C7:L7) -> 0
B8: Other Property Income | M8: =SUM(C8:L8) -> 0
B9: TOTAL INCOME | C9: =SUM(C7:C8) -> 0 | D9: =SUM(D7:D8) -> 0 | E9: =SUM(E7:E8) -> 0 | F9: =SUM(F7:F8) -> 0 | G9: =SUM(G7:G8) -> 0 | H9: =SUM(H7:H8) -> 0 | I9: =SUM(I7:I8) -> 0 | J9: =SUM(J7:J8) -> 0 | ... M9: =SUM(M7:M8) -> 0
B11: EXPENSES (HMRC SA105 Categories)
B12: Rent, rates, insurance & ground rent | M12: =SUM(C12:L12) -> 0
B13: Property repairs & maintenance | M13: =SUM(C13:L13) -> 0
B14: Loan interest & financial costs | M14: =SUM(C14:L14) -> 0
B15: Legal, management & professional fees | M15: =SUM(C15:L15) -> 0
B16: Cost of services (inc. wages) | M16: =SUM(C16:L16) -> 0
B17: Travel & vehicle costs | M17: =SUM(C17:L17) -> 0
B18: Allowable other expenses | M18: =SUM(C18:L18) -> 0
B19: TOTAL EXPENSES | C19: =SUM(C12:C18) -> 0 | D19: =SUM(D12:D18) -> 0 | E19: =SUM(E12:E18) -> 0 | F19: =SUM(F12:F18) -> 0 | G19: =SUM(G12:G18) -> 0 | H19: =SUM(H12:H18) -> 0 | I19: =SUM(I12:I18) -> 0 | J19: =SUM(J12:J18) -> 0 | ... M19: =SUM(M12:M18) -> 0
B21: NET PROFIT / (LOSS) | C21: =C9-C19 -> 0 | D21: =D9-D19 -> 0 | E21: =E9-E19 -> 0 | F21: =F9-F19 -> 0 | G21: =G9-G19 -> 0 | H21: =H9-H19 -> 0 | I21: =I9-I19 -> 0 | J21: =J9-J19 -> 0 | ... M21: =M9-M19 -> 0
B23: SA105 Reference: Box 20 = Total rents, Box 25-31 = Expenses by category. Hover over expense names for SA105 box references.

Sheet Jan
B2: January 2027 — Income & Expenses
B3: Tax Year 2026/27 | Quarter 4 | Enter amounts in blue cells
B5: Category | C5: ='Property Setup'!C6 -> 0 | D5: ='Property Setup'!D6 -> 0 | E5: ='Property Setup'!E6 -> 0 | F5: ='Property Setup'!F6 -> 0 | G5: ='Property Setup'!G6 -> 0 | H5: ='Property Setup'!H6 -> 0 | I5: ='Property Setup'!I6 -> 0 | J5: ='Property Setup'!J6 -> 0 | ... L5: ='Property Setup'!L6 -> 0 | M5: TOTAL
B6: INCOME
B7: Rental Income Received | M7: =SUM(C7:L7) -> 0
B8: Other Property Income | M8: =SUM(C8:L8) -> 0
B9: TOTAL INCOME | C9: =SUM(C7:C8) -> 0 | D9: =SUM(D7:D8) -> 0 | E9: =SUM(E7:E8) -> 0 | F9: =SUM(F7:F8) -> 0 | G9: =SUM(G7:G8) -> 0 | H9: =SUM(H7:H8) -> 0 | I9: =SUM(I7:I8) -> 0 | J9: =SUM(J7:J8) -> 0 | ... M9: =SUM(M7:M8) -> 0
B11: EXPENSES (HMRC SA105 Categories)
B12: Rent, rates, insurance & ground rent | M12: =SUM(C12:L12) -> 0
B13: Property repairs & maintenance | M13: =SUM(C13:L13) -> 0
B14: Loan interest & financial costs | M14: =SUM(C14:L14) -> 0
B15: Legal, management & professional fees | M15: =SUM(C15:L15) -> 0
B16: Cost of services (inc. wages) | M16: =SUM(C16:L16) -> 0
B17: Travel & vehicle costs | M17: =SUM(C17:L17) -> 0
B18: Allowable other expenses | M18: =SUM(C18:L18) -> 0
B19: TOTAL EXPENSES | C19: =SUM(C12:C18) -> 0 | D19: =SUM(D12:D18) -> 0 | E19: =SUM(E12:E18) -> 0 | F19: =SUM(F12:F18) -> 0 | G19: =SUM(G12:G18) -> 0 | H19: =SUM(H12:H18) -> 0 | I19: =SUM(I12:I18) -> 0 | J19: =SUM(J12:J18) -> 0 | ... M19: =SUM(M12:M18) -> 0
B21: NET PROFIT / (LOSS) | C21: =C9-C19 -> 0 | D21: =D9-D19 -> 0 | E21: =E9-E19 -> 0 | F21: =F9-F19 -> 0 | G21: =G9-G19 -> 0 | H21: =H9-H19 -> 0 | I21: =I9-I19 -> 0 | J21: =J9-J19 -> 0 | ... M21: =M9-M19 -> 0
B23: SA105 Reference: Box 20 = Total rents, Box 25-31 = Expenses by category. Hover over expense names for SA105 box references.

Sheet Feb
B2: February 2027 — Income & Expenses
B3: Tax Year 2026/27 | Quarter 4 | Enter amounts in blue cells
B5: Category | C5: ='Property Setup'!C6 -> 0 | D5: ='Property Setup'!D6 -> 0 | E5: ='Property Setup'!E6 -> 0 | F5: ='Property Setup'!F6 -> 0 | G5: ='Property Setup'!G6 -> 0 | H5: ='Property Setup'!H6 -> 0 | I5: ='Property Setup'!I6 -> 0 | J5: ='Property Setup'!J6 -> 0 | ... L5: ='Property Setup'!L6 -> 0 | M5: TOTAL
B6: INCOME
B7: Rental Income Received | M7: =SUM(C7:L7) -> 0
B8: Other Property Income | M8: =SUM(C8:L8) -> 0
B9: TOTAL INCOME | C9: =SUM(C7:C8) -> 0 | D9: =SUM(D7:D8) -> 0 | E9: =SUM(E7:E8) -> 0 | F9: =SUM(F7:F8) -> 0 | G9: =SUM(G7:G8) -> 0 | H9: =SUM(H7:H8) -> 0 | I9: =SUM(I7:I8) -> 0 | J9: =SUM(J7:J8) -> 0 | ... M9: =SUM(M7:M8) -> 0
B11: EXPENSES (HMRC SA105 Categories)
B12: Rent, rates, insurance & ground rent | M12: =SUM(C12:L12) -> 0
B13: Property repairs & maintenance | M13: =SUM(C13:L13) -> 0
B14: Loan interest & financial costs | M14: =SUM(C14:L14) -> 0
B15: Legal, management & professional fees | M15: =SUM(C15:L15) -> 0
B16: Cost of services (inc. wages) | M16: =SUM(C16:L16) -> 0
B17: Travel & vehicle costs | M17: =SUM(C17:L17) -> 0
B18: Allowable other expenses | M18: =SUM(C18:L18) -> 0
B19: TOTAL EXPENSES | C19: =SUM(C12:C18) -> 0 | D19: =SUM(D12:D18) -> 0 | E19: =SUM(E12:E18) -> 0 | F19: =SUM(F12:F18) -> 0 | G19: =SUM(G12:G18) -> 0 | H19: =SUM(H12:H18) -> 0 | I19: =SUM(I12:I18) -> 0 | J19: =SUM(J12:J18) -> 0 | ... M19: =SUM(M12:M18) -> 0
B21: NET PROFIT / (LOSS) | C21: =C9-C19 -> 0 | D21: =D9-D19 -> 0 | E21: =E9-E19 -> 0 | F21: =F9-F19 -> 0 | G21: =G9-G19 -> 0 | H21: =H9-H19 -> 0 | I21: =I9-I19 -> 0 | J21: =J9-J19 -> 0 | ... M21: =M9-M19 -> 0
B23: SA105 Reference: Box 20 = Total rents, Box 25-31 = Expenses by category. Hover over expense names for SA105 box references.

Sheet Mar
B2: March 2027 — Income & Expenses
B3: Tax Year 2026/27 | Quarter 4 | Enter amounts in blue cells
B5: Category | C5: ='Property Setup'!C6 -> 0 | D5: ='Property Setup'!D6 -> 0 | E5: ='Property Setup'!E6 -> 0 | F5: ='Property Setup'!F6 -> 0 | G5: ='Property Setup'!G6 -> 0 | H5: ='Property Setup'!H6 -> 0 | I5: ='Property Setup'!I6 -> 0 | J5: ='Property Setup'!J6 -> 0 | ... L5: ='Property Setup'!L6 -> 0 | M5: TOTAL
B6: INCOME
B7: Rental Income Received | M7: =SUM(C7:L7) -> 0
B8: Other Property Income | M8: =SUM(C8:L8) -> 0
B9: TOTAL INCOME | C9: =SUM(C7:C8) -> 0 | D9: =SUM(D7:D8) -> 0 | E9: =SUM(E7:E8) -> 0 | F9: =SUM(F7:F8) -> 0 | G9: =SUM(G7:G8) -> 0 | H9: =SUM(H7:H8) -> 0 | I9: =SUM(I7:I8) -> 0 | J9: =SUM(J7:J8) -> 0 | ... M9: =SUM(M7:M8) -> 0
B11: EXPENSES (HMRC SA105 Categories)
B12: Rent, rates, insurance & ground rent | M12: =SUM(C12:L12) -> 0
B13: Property repairs & maintenance | M13: =SUM(C13:L13) -> 0
B14: Loan interest & financial costs | M14: =SUM(C14:L14) -> 0
B15: Legal, management & professional fees | M15: =SUM(C15:L15) -> 0
B16: Cost of services (inc. wages) | M16: =SUM(C16:L16) -> 0
B17: Travel & vehicle costs | M17: =SUM(C17:L17) -> 0
B18: Allowable other expenses | M18: =SUM(C18:L18) -> 0
B19: TOTAL EXPENSES | C19: =SUM(C12:C18) -> 0 | D19: =SUM(D12:D18) -> 0 | E19: =SUM(E12:E18) -> 0 | F19: =SUM(F12:F18) -> 0 | G19: =SUM(G12:G18) -> 0 | H19: =SUM(H12:H18) -> 0 | I19: =SUM(I12:I18) -> 0 | J19: =SUM(J12:J18) -> 0 | ... M19: =SUM(M12:M18) -> 0
B21: NET PROFIT / (LOSS) | C21: =C9-C19 -> 0 | D21: =D9-D19 -> 0 | E21: =E9-E19 -> 0 | F21: =F9-F19 -> 0 | G21: =G9-G19 -> 0 | H21: =H9-H19 -> 0 | I21: =I9-I19 -> 0 | J21: =J9-J19 -> 0 | ... M21: =M9-M19 -> 0
B23: SA105 Reference: Box 20 = Total rents, Box 25-31 = Expenses by category. Hover over expense names for SA105 box references.

Sheet Quarterly MTD
B2: Making Tax Digital — Quarterly Summary
B3: Tax Year 2026/27 | Auto-calculated from monthly tabs | Submit to HMRC via MTD software
B5: Category | C5: Q1 (Apr-Jun) | D5: Q2 (Jul-Sep) | E5: Q3 (Oct-Dec) | F5: Q4 (Jan-Mar) | G5: FULL YEAR
B6: INCOME
B7: Rental Income Received | C7: =Apr!M7+May!M7+Jun!M7 -> 0 | D7: =Jul!M7+Aug!M7+Sep!M7 -> 0 | E7: =Oct!M7+Nov!M7+Dec!M7 -> 0 | F7: =Jan!M7+Feb!M7+Mar!M7 -> 0 | G7: =SUM(C7:F7) -> 0
B8: Other Property Income | C8: =Apr!M8+May!M8+Jun!M8 -> 0 | D8: =Jul!M8+Aug!M8+Sep!M8 -> 0 | E8: =Oct!M8+Nov!M8+Dec!M8 -> 0 | F8: =Jan!M8+Feb!M8+Mar!M8 -> 0 | G8: =SUM(C8:F8) -> 0
B9: TOTAL INCOME | C9: =SUM(C7:C8) -> 0 | D9: =SUM(D7:D8) -> 0 | E9: =SUM(E7:E8) -> 0 | F9: =SUM(F7:F8) -> 0 | G9: =SUM(G7:G8) -> 0
B11: EXPENSES (HMRC SA105 Categories)
B12: Rent, rates, insurance & ground rent | C12: =Apr!M12+May!M12+Jun!M12 -> 0 | D12: =Jul!M12+Aug!M12+Sep!M12 -> 0 | E12: =Oct!M12+Nov!M12+Dec!M12 -> 0 | F12: =Jan!M12+Feb!M12+Mar!M12 -> 0 | G12: =SUM(C12:F12) -> 0
B13: Property repairs & maintenance | C13: =Apr!M13+May!M13+Jun!M13 -> 0 | D13: =Jul!M13+Aug!M13+Sep!M13 -> 0 | E13: =Oct!M13+Nov!M13+Dec!M13 -> 0 | F13: =Jan!M13+Feb!M13+Mar!M13 -> 0 | G13: =SUM(C13:F13) -> 0
B14: Loan interest & financial costs | C14: =Apr!M14+May!M14+Jun!M14 -> 0 | D14: =Jul!M14+Aug!M14+Sep!M14 -> 0 | E14: =Oct!M14+Nov!M14+Dec!M14 -> 0 | F14: =Jan!M14+Feb!M14+Mar!M14 -> 0 | G14: =SUM(C14:F14) -> 0
B15: Legal, management & professional fees | C15: =Apr!M15+May!M15+Jun!M15 -> 0 | D15: =Jul!M15+Aug!M15+Sep!M15 -> 0 | E15: =Oct!M15+Nov!M15+Dec!M15 -> 0 | F15: =Jan!M15+Feb!M15+Mar!M15 -> 0 | G15: =SUM(C15:F15) -> 0
B16: Cost of services (inc. wages) | C16: =Apr!M16+May!M16+Jun!M16 -> 0 | D16: =Jul!M16+Aug!M16+Sep!M16 -> 0 | E16: =Oct!M16+Nov!M16+Dec!M16 -> 0 | F16: =Jan!M16+Feb!M16+Mar!M16 -> 0 | G16: =SUM(C16:F16) -> 0
B17: Travel & vehicle costs | C17: =Apr!M17+May!M17+Jun!M17 -> 0 | D17: =Jul!M17+Aug!M17+Sep!M17 -> 0 | E17: =Oct!M17+Nov!M17+Dec!M17 -> 0 | F17: =Jan!M17+Feb!M17+Mar!M17 -> 0 | G17: =SUM(C17:F17) -> 0
B18: Allowable other expenses | C18: =Apr!M18+May!M18+Jun!M18 -> 0 | D18: =Jul!M18+Aug!M18+Sep!M18 -> 0 | E18: =Oct!M18+Nov!M18+Dec!M18 -> 0 | F18: =Jan!M18+Feb!M18+Mar!M18 -> 0 | G18: =SUM(C18:F18) -> 0
B19: TOTAL EXPENSES | C19: =SUM(C12:C18) -> 0 | D19: =SUM(D12:D18) -> 0 | E19: =SUM(E12:E18) -> 0 | F19: =SUM(F12:F18) -> 0 | G19: =SUM(G12:G18) -> 0
B21: NET PROFIT / (LOSS) | C21: =C9-C19 -> 0 | D21: =D9-D19 -> 0 | E21: =E9-E19 -> 0 | F21: =F9-F19 -> 0 | G21: =G9-G19 -> 0
B23: MORTGAGE INTEREST (20% Tax Credit)
B24: Finance costs (from expenses above) | C24: =C14 -> 0 | D24: =D14 -> 0 | E24: =E14 -> 0 | F24: =F14 -> 0 | G24: =G14 -> 0
B25: 20% Tax Credit on Finance Costs | C25: =C24*0.2 -> 0 | D25: =D24*0.2 -> 0 | E25: =E24*0.2 -> 0 | F25: =F24*0.2 -> 0 | G25: =G24*0.2 -> 0
B27: MTD SUBMISSION DEADLINES
B28: Q1 (Apr-Jun 2026) | C28: 7 August 2026
B29: Q2 (Jul-Sep 2026) | C29: 7 November 2026
B30: Q3 (Oct-Dec 2026) | C30: 7 February 2027
B31: Q4 (Jan-Mar 2027) | C31: 7 May 2027

Sheet Annual Summary
B2: Annual Summary — Tax Year 2026/27
B3: Auto-calculated from Quarterly MTD tab | For Self Assessment SA105
C5: Amount (£) | D5: SA105 Box
B6: Total Rents & Other Income | C6: ='Quarterly MTD'!G9 -> 0 | D6: Box 20
B7: Rent, rates, insurance & ground rent | C7: ='Quarterly MTD'!G12 -> 0 | D7: Box 25
B8: Property repairs & maintenance | C8: ='Quarterly MTD'!G13 -> 0 | D8: Box 26
B9: Loan interest & financial costs | C9: ='Quarterly MTD'!G14 -> 0 | D9: Box 27
B10: Legal, management & professional fees | C10: ='Quarterly MTD'!G15 -> 0 | D10: Box 28
B11: Cost of services (inc. wages) | C11: ='Quarterly MTD'!G16 -> 0 | D11: Box 29
B12: Travel & vehicle costs | C12: ='Quarterly MTD'!G17 -> 0 | D12: Box 30
B13: Allowable other expenses | C13: ='Quarterly MTD'!G18 -> 0 | D13: Box 31
B14: Total Allowable Expenses | C14: ='Quarterly MTD'!G19 -> 0 | D14: Box 32
B16: NET PROPERTY INCOME / (LOSS) | C16: ='Quarterly MTD'!G21 -> 0 | D16: Box 38
B18: TAX ESTIMATE (for guidance only — consult your accountant)
B19: Your Income Tax Rate | C19: 0.2 | D19: Enter 20%, 40% or 45%
B20: Estimated Tax on Property Income | C20: =IF(C16>0,C16*C19,0) -> 0
B21: Less: 20% Mortgage Interest Tax Credit | C21: ='Quarterly MTD'!G24*0.2 -> 0
B22: ESTIMATED NET TAX DUE | C22: =MAX(0,C20-C21) -> 0
B24: Note: This is an estimate only. Actual tax liability depends on your total income from all sources, personal allowance, and other factors. The 20% mortgage interest tax credit applies to all taxpayers regardless of their tax band. Always consult a qualified accountant.
